basic_division/__init__.py
basic_division/division.py
basic_multplication/__init__.py
basic_multplication/multiplication.py
basic_maths-0.1.20.dist-info/METADATA
basic_maths-0.1.20.dist-info/WHEEL
basic_maths-0.1.20.dist-info/top_level.txt
basic_maths-0.1.20.dist-info/RECORD
